ydpic/__init__.py
ydpic/config.ini
ydpic/config.py
ydpic/note_tpl.xml
ydpic/yd_loginer.py
ydpic/yd_note.py
ydpic/ydpic.py
ydpic-0.2.2.dist-info/LICENSE
ydpic-0.2.2.dist-info/METADATA
ydpic-0.2.2.dist-info/WHEEL
ydpic-0.2.2.dist-info/entry_points.txt
ydpic-0.2.2.dist-info/top_level.txt
ydpic-0.2.2.dist-info/RECORD
